key_flip/__init__.py
key_flip/cli/__init__.py
key_flip/cli/__main__.py
key_flip/core/__init__.py
key_flip/core/converters.py
key_flip/core/errors.py
key_flip/core/interfaces.py
key_flip/core/layouts.py
key_flip/core/models.py
key_flip/core/repository.py
key_flip/core/types.py
key_flip-0.1.0.dist-info/METADATA
key_flip-0.1.0.dist-info/WHEEL
key_flip-0.1.0.dist-info/entry_points.txt
key_flip-0.1.0.dist-info/licenses/LICENSE
key_flip-0.1.0.dist-info/RECORD
