Metadata-Version: 2.4
Name: key-flip
Version: 0.1.0
Summary: key-flip is a utility that fixes text typed with the wrong keyboard layout.
Project-URL: changelog, https://theveenrok.github.io/key-flip/changelog
Project-URL: documentation, https://theveenrok.github.io/key-flip/
Project-URL: funding, https://theveenrok.github.io/key-flip/funding
Project-URL: homepage, https://github.com/theveenrok/key-flip
Project-URL: issues, https://github.com/theveenrok/key-flip/issues
Project-URL: releasenotes, https://github.com/theveenrok/key-flip/releases
Project-URL: source, https://github.com/theveenrok/key-flip
Author-email: Vlad Korneev <veenrok@veenrok.com>
Maintainer-email: Vlad Korneev <veenrok@veenrok.com>
License: MIT License
License-File: LICENSE
Keywords: cli,converter,flip,keyboard,keymap,layout,text-input,typing,utility
Classifier: Programming Language :: Python :: 3 :: Only
Classifier: Programming Language :: Python :: 3.13
Classifier: Programming Language :: Python :: 3.14
Requires-Python: >=3.13
